client.py
global_refer.py
mcp_inspector.py
mcp_server_inspector-1.2.0.dist-info/METADATA
mcp_server_inspector-1.2.0.dist-info/WHEEL
mcp_server_inspector-1.2.0.dist-info/entry_points.txt
mcp_server_inspector-1.2.0.dist-info/top_level.txt
mcp_server_inspector-1.2.0.dist-info/RECORD
