Metadata-Version: 2.4
Name: mcp-server-inspector
Version: 1.2.0
Summary: MCP服务器检查和连接工具 - 支持自动检测SSE和Streamable HTTP类型
Author-email: xray918 <xray918@example.com>
License: MIT
Project-URL: Homepage, https://github.com/xray918/mcp-server-inspector
Project-URL: Repository, https://github.com/xray918/mcp-server-inspector.git
Project-URL: Issues, https://github.com/xray918/mcp-server-inspector/issues
Keywords: mcp,server,inspector,sse,http,cli
Classifier: Development Status :: 4 - Beta
Classifier: Environment :: Console
Classifier: Intended Audience :: Developers
Classifier: License :: OSI Approved :: MIT License
Classifier: Operating System :: OS Independent
Classifier: Programming Language :: Python :: 3
Classifier: Programming Language :: Python :: 3.10
Classifier: Programming Language :: Python :: 3.11
Classifier: Programming Language :: Python :: 3.12
Classifier: Topic :: Software Development :: Libraries :: Python Modules
Classifier: Topic :: System :: Networking
Classifier: Topic :: Utilities
Requires-Python: >=3.10
Requires-Dist: mcp>=1.13.0
Requires-Dist: openai>=1.6.0
Requires-Dist: python-dotenv>=1.0.0
Requires-Dist: aiohttp>=3.8.0
Provides-Extra: dev
Requires-Dist: pytest>=7.0.0; extra == "dev"
Requires-Dist: pytest-asyncio>=0.21.0; extra == "dev"
Requires-Dist: pytest-cov>=4.0.0; extra == "dev"
Requires-Dist: black>=23.0.0; extra == "dev"
Requires-Dist: isort>=5.12.0; extra == "dev"
Requires-Dist: flake8>=6.0.0; extra == "dev"
Requires-Dist: mypy>=1.5.0; extra == "dev"
